toughcli/__init__.py
toughcli/settings.py
toughcli/toughclis.py
toughcli/service/__init__.py
toughcli/service/docker.py
toughcli/service/mysql.py
toughcli/service/radius.py
toughcli/service/redis.py
toughcli/service/toughbt.py
toughcli/service/txportal.py
toughcli/service/wlan.py
toughcli-0.1.2.4.dist-info/DESCRIPTION.rst
toughcli-0.1.2.4.dist-info/METADATA
toughcli-0.1.2.4.dist-info/RECORD
toughcli-0.1.2.4.dist-info/WHEEL
toughcli-0.1.2.4.dist-info/eager_resources.txt
toughcli-0.1.2.4.dist-info/entry_points.txt
toughcli-0.1.2.4.dist-info/metadata.json
toughcli-0.1.2.4.dist-info/top_level.txt
toughcli-0.1.2.4.dist-info/zip-safe
